setup.py
iw/__init__.py
iw.subscriber.egg-info/PKG-INFO
iw.subscriber.egg-info/SOURCES.txt
iw.subscriber.egg-info/dependency_links.txt
iw.subscriber.egg-info/namespace_packages.txt
iw.subscriber.egg-info/not-zip-safe
iw.subscriber.egg-info/requires.txt
iw.subscriber.egg-info/top_level.txt
iw/subscriber/CHANGES
iw/subscriber/README.txt
iw/subscriber/__init__.py
iw/subscriber/adapters.py
iw/subscriber/annotation.py
iw/subscriber/catalog.py
iw/subscriber/config.py
iw/subscriber/configure.zcml
iw/subscriber/i18n.py
iw/subscriber/i18n.sh
iw/subscriber/interfaces.py
iw/subscriber/mailer.zcml
iw/subscriber/setuphandlers.py
iw/subscriber/utility.py
iw/subscriber/utils.py
iw/subscriber/vocabularies.py
iw/subscriber/browser/__init__.py
iw/subscriber/browser/actions.py
iw/subscriber/browser/ajax.py
iw/subscriber/browser/configure.zcml
iw/subscriber/browser/subscribe.py
iw/subscriber/browser/tick.py
iw/subscriber/browser/utility.py
iw/subscriber/browser/static/main.css
iw/subscriber/browser/static/main.js
iw/subscriber/browser/static/main.kss
iw/subscriber/browser/templates/body.pt
iw/subscriber/browser/templates/subject.pt
iw/subscriber/docs/README.txt
iw/subscriber/doctests/README.txt
iw/subscriber/doctests/actions.txt
iw/subscriber/doctests/ajax.txt
iw/subscriber/doctests/annotations.txt
iw/subscriber/doctests/catalog.txt
iw/subscriber/doctests/functionnal.txt
iw/subscriber/doctests/mailer.txt
iw/subscriber/doctests/tick.txt
iw/subscriber/doctests/utility.txt
iw/subscriber/locales/iw.subscriber-fr.po
iw/subscriber/locales/iw.subscriber.pot
iw/subscriber/locales/fr/LC_MESSAGES/iw.subscriber.mo
iw/subscriber/profiles/default/actionicons.xml
iw/subscriber/profiles/default/actions.xml
iw/subscriber/profiles/default/catalog.xml
iw/subscriber/profiles/default/controlpanel.xml
iw/subscriber/profiles/default/cssregistry.xml
iw/subscriber/profiles/default/import_steps.xml
iw/subscriber/profiles/default/iw.subscriber.various.txt
iw/subscriber/profiles/default/jsregistry.xml
iw/subscriber/tests/__init__.py
iw/subscriber/tests/base.py
iw/subscriber/tests/test_docstrings.py
iw/subscriber/tests/test_subscriberdocs.py
