Metadata-Version: 1.0
Name: iw.subscriber
Version: 0.1.1
Summary: This package allow Plone users to subscribe to contents. Then they will be notified on all creation/modification on this contents.
Home-page: https://ingeniweb.svn.sourceforge.net/svnroot/ingeniweb/iw.subscriber
Author: Ingeniweb
Author-email: support@ingeniweb.com
License: GPL
Keywords: zope plone
Platform: UNKNOWN
Classifier: Framework :: Plone
Classifier: Framework :: Zope2
Classifier: Framework :: Zope3
Classifier: Programming Language :: Python
Classifier: Topic :: Software Development :: Libraries :: Python Modules
